balancer/__init__.py
balancer/__main__.py
balancer/atomic_mass.py
balancer/errors.py
balancer/pipeline_base.py
balancer/pipeline_contracts.py
balancer/pipeline_stages/compute_stage.py
balancer/pipeline_stages/format_stage.py
balancer/pipeline_stages/input_stage.py
balancer/pipeline_stages/output_stage.py
balancer/pipeline_stages/parse_stage.py
balancer/templates/input_template.md
reaction_balancer-2.0.7.dist-info/METADATA
reaction_balancer-2.0.7.dist-info/WHEEL
reaction_balancer-2.0.7.dist-info/entry_points.txt
reaction_balancer-2.0.7.dist-info/licenses/LICENSE
reaction_balancer-2.0.7.dist-info/RECORD
