Metadata-Version: 2.4
Name: reaction-balancer
Version: 2.0.7
Summary: Balance chemical equations and generate printable forms
Project-URL: Homepage, https://github.com/ponyofshadows/balancer
Project-URL: Source, https://github.com/ponyofshadows/balancer
Project-URL: Issues, https://github.com/ponyofshadows/balancer/issues
Author: ponyofshadows
License-Expression: MIT
License-File: LICENSE
Keywords: chemical-equation,chemical-reactions,chemistry,condensed-matter,materials-science,openpyxl,solid-state-chemistry,solid-state-synthesis,stoichiometry,superconductivity,sympy,synthesis-calculation
Classifier: Intended Audience :: Education
Classifier: Intended Audience :: Science/Research
Classifier: License :: OSI Approved :: MIT License
Classifier: Operating System :: OS Independent
Classifier: Programming Language :: Python :: 3.11
Classifier: Topic :: Scientific/Engineering
Classifier: Topic :: Scientific/Engineering :: Chemistry
Classifier: Topic :: Scientific/Engineering :: Physics
Requires-Python: >=3.11
Requires-Dist: openpyxl<4.0,>=3.1.5
Requires-Dist: sympy<2.0,>=1.14.0
